djangorestframework_msgpack-1.0.2.dist-info/DESCRIPTION.rst
djangorestframework_msgpack-1.0.2.dist-info/METADATA
djangorestframework_msgpack-1.0.2.dist-info/RECORD
djangorestframework_msgpack-1.0.2.dist-info/WHEEL
djangorestframework_msgpack-1.0.2.dist-info/metadata.json
djangorestframework_msgpack-1.0.2.dist-info/top_level.txt
rest_framework_msgpack/__init__.py
rest_framework_msgpack/models.py
rest_framework_msgpack/parsers.py
rest_framework_msgpack/renderers.py
rest_framework_msgpack/tests.py
