Metadata-Version: 2.0
Name: djangorestframework-msgpack
Version: 1.0.2
Summary: MessagePack support for Django REST framework
Home-page: http://github.com/juanriaza/django-rest-framework-msgpack
Author: Juan Riaza
Author-email: juanriaza@gmail.com
License: BSD
Platform: UNKNOWN
Classifier: Development Status :: 4 - Beta
Classifier: Environment :: Web Environment
Classifier: Framework :: Django
Classifier: Intended Audience :: Developers
Classifier: License :: OSI Approved :: BSD License
Classifier: Operating System :: OS Independent
Classifier: Programming Language :: Python
Classifier: Topic :: Internet :: WWW/HTTP
Requires-Dist: Django (>=1.8)
Requires-Dist: djangorestframework (>=2.1.15)
Requires-Dist: msgpack-python (>=0.2.4)
Requires-Dist: python-dateutil (>=2.1)
